Workbook

Sheet Portada
A1: Flujo de Efectivo Proyectado - Caso Manufacturas Técnicas del Caribe S.A.S. (caso ilustrativo)
A2: Registro de Operaciones Contables I - Unidad 3: Presentación de estados financieros - Cifras en millones de pesos colombianos (COP)
A4: Etiqueta | B4: [ROC1][Avanzado][21092026][ArizaPacheco]
A5: Estudiante | B5: Tatiana María Ariza Pacheco
A6: Institución | B6: Corporación Universitaria Americana
A7: Versión del libro | B7: 1.0 (21/09/2026)
A8: Software | B8: Microsoft Excel (compatible con Excel 2016 o superior; solo usa funciones básicas)
A9: Marco normativo | B9: NIC 7 Estado de Flujos de Efectivo (NIIF) - método indirecto con conciliación por método directo
A10: Nota | B10: La empresa y sus cifras son un caso ilustrativo construido para este reto; deben reemplazarse si el docente entrega datos propios.
A12: Convención de colores
A13: Azul: dato de entrada o supuesto (editable)
A14: Negro: fórmula de cálculo
A15: Verde: vínculo directo a otra hoja
A16: Fondo amarillo: campo a completar por el estudiante / revisor
A18: Índice de hojas
A19: Supuestos | B19: Supuestos cuantitativos con justificación y referencia a NIC 7
A20: Historicos | B20: Estado de resultados y balance histórico (Año -1 y Año 0)
A21: Ratios | B21: Ratios de liquidez, actividad y endeudamiento
A22: ER_Proy | B22: Estado de resultados proyectado (Año 1)
A23: Balance_Proy | B23: Balance proyectado (Año 1) con verificación de cuadre
A24: Flujo_Indirecto | B24: Estado de flujos de efectivo (método indirecto): Año 0 comparativo y Año 1 proyectado
A25: Flujo_Directo | B25: Presentación por método directo y conciliación con el indirecto
A26: Validacion | B26: Controles automáticos, lista de verificación NIC 7 y registro de revisión técnica
A27: Anexo_Formulas | B27: Documentación de las fórmulas utilizadas

Sheet Supuestos
A1: Supuestos cuantitativos del Año 1
A2: Cifras en millones de COP salvo indicación. Celdas azules = editables; todo el modelo recalcula a partir de ellas.
A4: Supuesto | B4: Valor | C4: Unidad | D4: Justificación | E4: Referencia normativa
A5: Crecimiento de ventas netas | B5: 0.08 | C5: % anual | D5: El Año 0 creció 10,0 %; se modera por uso cercano a la capacidad instalada y demanda incierta. | E5: NIC 7 párr. 14(a)
A6: Costo de ventas (sin depreciación) / ventas | B6: 0.645 | C6: % de ventas | D6: Igual a la razón del Año 0 (64,5 %); no se asumen mejoras de margen por prudencia. | E6: NIC 2; NIC 7 párr. 14(c)
A7: Crecimiento de gastos de administración | B7: 0.05 | C7: % anual | D7: Ajuste salarial e inflacionario esperado. | E7: NIC 7 párr. 14(d)
A8: Gastos de ventas / ventas | B8: 0.074 | C8: % de ventas | D8: Se mantiene la proporción del Año 0 (7,4 %). | E8: NIC 7 párr. 14(d)
A9: Tasa de depreciación | B9: 0.1 | C9: % anual | D9: Aplicada sobre PP&E neto inicial más 50 % del capex (adiciones a mitad de año). El Año 0 fue ~9,9 %. | E9: NIC 16; NIC 7 párr. 20
A10: Renovación de maquinaria (capex) | B10: 1200 | C10: COP mm | D10: Reposición de líneas con alta obsolescencia; supera la depreciación para sostener capacidad. | E10: NIC 7 párr. 16(a)
A11: Plazo de cobro a clientes | B11: 60 | C11: días | D11: Año 0: 59,5 días; se mantiene la política de crédito a 60 días. | E11: NIC 7 párr. 14(a) y 20(a)
A12: Rotación de inventarios | B12: 85 | C12: días | D12: Año 0: 86,7 días; leve mejora por gestión de compras. | E12: NIC 2; NIC 7 párr. 20(a)
A13: Plazo de pago a proveedores | B13: 58 | C13: días | D13: Año 0: 58,7 días; se mantiene el plazo negociado. | E13: NIC 7 párr. 14(c) y 20(a)
A14: Gastos pagados por anticipado / ventas | B14: 0.01 | C14: % de ventas | D14: Año 0: 1,0 %. | E14: NIC 7 párr. 20(a)
A15: Obligaciones laborales por pagar / ventas | B15: 0.022 | C15: % de ventas | D15: Año 0: 2,2 %. | E15: NIC 7 párr. 14(d)
A16: Tarifa de impuesto de renta | B16: 0.35 | C16: % de la utilidad antes de impuestos | D16: Tarifa general del impuesto de renta para sociedades en Colombia (verificar vigencia). | E16: NIC 12; NIC 7 párr. 35
... A24: Días del año comercial | B24: 365 | C24: días | D24: Convención para calcular plazos. | E24: -

Sheet Historicos
A1: Estados financieros históricos
A2: Cifras en millones de COP. Año 0 = último cierre; Año -1 = cierre anterior. Datos ilustrativos (azul).
A4: Concepto | B4: Año -1 | C4: Año 0
A5: Estado de resultados
A6: Ventas netas | B6: 18400 | C6: 20240
A7: Costo de ventas (sin depreciación) | B7: 11960 | C7: 13055
A8: Utilidad bruta | B8: =B6-B7 -> 6440 | C8: =C6-C7 -> 7185
A9: Gastos de administración | B9: 1840 | C9: 1960
A10: Gastos de ventas | B10: 1380 | C10: 1500
A11: Depreciación y amortización | B11: 900 | C11: 950
A12: Utilidad operacional | B12: =B8-B9-B10-B11 -> 2320 | C12: =C8-C9-C10-C11 -> 2775
A13: Gastos financieros | B13: 380 | C13: 410
A14: Utilidad antes de impuestos | B14: =B12-B13 -> 1940 | C14: =C12-C13 -> 2365
A15: Impuesto de renta | B15: 679 | C15: 828
A16: Utilidad neta | B16: =B14-B15 -> 1261 | C16: =C14-C15 -> 1537
A18: Balance general
A19: Efectivo y equivalentes de efectivo | B19: 1523 | C19: 1450
A20: Cuentas por cobrar comerciales | B20: 3000 | C20: 3300
A21: Inventarios | B21: 2900 | C21: 3100
A22: Gastos pagados por anticipado | B22: 180 | C22: 200
A23: Total activo corriente | B23: =SUM(B19:B22) -> 7603 | C23: =SUM(C19:C22) -> 8050
A24: Propiedades, planta y equipo (neto) | B24: 10000 | C24: 9600
A25: Total activo | B25: =B23+B24 -> 17603 | C25: =C23+C24 -> 17650
A26: Proveedores | B26: 1950 | C26: 2100
A27: Obligaciones laborales por pagar | B27: 420 | C27: 450
A28: Impuesto de renta por pagar | B28: 270 | C28: 300
A29: Deuda financiera corriente | B29: 1000 | C29: 1000
A30: Total pasivo corriente | B30: =SUM(B26:B29) -> 3640 | C30: =SUM(C26:C29) -> 3850
A31: Deuda financiera no corriente | B31: 5000 | C31: 4000
A32: Total pasivo | B32: =B30+B31 -> 8640 | C32: =C30+C31 -> 7850
A33: Capital social | B33: 5000 | C33: 5000
A34: Reservas | B34: 1300 | C34: 1500
A35: Resultados acumulados | B35: 1402 | C35: 1763
A36: Utilidad del ejercicio | B36: =B16 -> 1261 | C36: =C16 -> 1537
A37: Total patrimonio | B37: =SUM(B33:B36) -> 8963 | C37: =SUM(C33:C36) -> 9800
A38: Total pasivo + patrimonio | B38: =B32+B37 -> 17603 | C38: =C32+C37 -> 17650
A39: Verificación (activo - pasivo - patrimonio; debe ser 0) | B39: =B25-B38 -> 0 | C39: =C25-C38 -> 0

Sheet ER_Proy
A1: Estado de resultados proyectado
A2: Cifras en millones de COP. Año 0 vinculado a Historicos; Año 1 calculado con Supuestos.
A4: Concepto | B4: Año 0 (histórico) | C4: Año 1 (proyectado) | D4: Variación %
A5: Ventas netas | B5: =Historicos!C6 -> 20240 | C5: =B5*(1+Supuestos!$B$5) -> 21859.2 | D5: =IF(B5=0,0,C5/B5-1) -> 0.08
A6: Costo de ventas (sin depreciación) | B6: =Historicos!C7 -> 13055 | C6: =C5*Supuestos!$B$6 -> 14099.184 | D6: =IF(B6=0,0,C6/B6-1) -> 0.079983455
A7: Utilidad bruta | B7: =B5-B6 -> 7185 | C7: =C5-C6 -> 7760.016 | D7: =IF(B7=0,0,C7/B7-1) -> 0.080030063
A8: Gastos de administración | B8: =Historicos!C9 -> 1960 | C8: =B8*(1+Supuestos!$B$7) -> 2058 | D8: =IF(B8=0,0,C8/B8-1) -> 0.05
A9: Gastos de ventas | B9: =Historicos!C10 -> 1500 | C9: =C5*Supuestos!$B$8 -> 1617.5808 | D9: =IF(B9=0,0,C9/B9-1) -> 0.0783872
A10: Depreciación y amortización | B10: =Historicos!C11 -> 950 | C10: =Supuestos!$B$9*(Historicos!C24+0.5*Supuestos!$B$10) -> 1020 | D10: =IF(B10=0,0,C10/B10-1) -> 0.073684211
A11: Utilidad operacional | B11: =B7-B8-B9-B10 -> 2775 | C11: =C7-C8-C9-C10 -> 3064.4352 | D11: =IF(B11=0,0,C11/B11-1) -> 0.10430097
A12: Gastos financieros | B12: =Historicos!C13 -> 410 | C12: =Supuestos!$B$18*(Historicos!C29+Historicos!C31+0.5*Supuestos!$B$19) -> 424 | D12: =IF(B12=0,0,C12/B12-1) -> 0.034146341
A13: Utilidad antes de impuestos | B13: =B11-B12 -> 2365 | C13: =C11-C12 -> 2640.4352 | D13: =IF(B13=0,0,C13/B13-1) -> 0.11646309
A14: Impuesto de renta | B14: =Historicos!C15 -> 828 | C14: =MAX(0,C13)*Supuestos!$B$16 -> 924.15232 | D14: =IF(B14=0,0,C14/B14-1) -> 0.11612599
A15: Utilidad neta | B15: =B13-B14 -> 1537 | C15: =C13-C14 -> 1716.2829 | D15: =IF(B15=0,0,C15/B15-1) -> 0.11664468

Sheet Balance_Proy
A1: Balance general proyectado
A2: Cifras en millones de COP. El efectivo del Año 1 proviene del estado de flujos de efectivo (Flujo_Indirecto).
A4: Concepto | B4: Año 0 (histórico) | C4: Año 1 (proyectado)
A5: Efectivo y equivalentes de efectivo | B5: =Historicos!C19 -> 1450 | C5: =Flujo_Indirecto!C27 -> 1526.5416
A6: Cuentas por cobrar comerciales | B6: =Historicos!C20 -> 3300 | C6: =ER_Proy!C5*Supuestos!$B$11/Supuestos!$B$24 -> 3593.2932
A7: Inventarios | B7: =Historicos!C21 -> 3100 | C7: =ER_Proy!C6*Supuestos!$B$12/Supuestos!$B$24 -> 3283.3716
A8: Gastos pagados por anticipado | B8: =Historicos!C22 -> 200 | C8: =ER_Proy!C5*Supuestos!$B$14 -> 218.592
A9: Total activo corriente | B9: =SUM(B5:B8) -> 8050 | C9: =SUM(C5:C8) -> 8621.7984
A10: Propiedades, planta y equipo (neto) | B10: =Historicos!C24 -> 9600 | C10: =B10+Supuestos!$B$10-ER_Proy!C10 -> 9780
A11: Total activo | B11: =B9+B10 -> 17650 | C11: =C9+C10 -> 18401.798
A12: Proveedores | B12: =Historicos!C26 -> 2100 | C12: =ER_Proy!C6*Supuestos!$B$13/Supuestos!$B$24 -> 2240.4183
A13: Obligaciones laborales por pagar | B13: =Historicos!C27 -> 450 | C13: =ER_Proy!C5*Supuestos!$B$15 -> 480.9024
A14: Impuesto de renta por pagar | B14: =Historicos!C28 -> 300 | C14: =ER_Proy!C14*Supuestos!$B$17 -> 332.69484
A15: Deuda financiera corriente | B15: =Historicos!C29 -> 1000 | C15: =Supuestos!$B$21 -> 1000
A16: Total pasivo corriente | B16: =SUM(B12:B15) -> 3850 | C16: =SUM(C12:C15) -> 4054.0155
A17: Deuda financiera no corriente | B17: =Historicos!C31 -> 4000 | C17: =(Historicos!C29+Historicos!C31+Supuestos!$B$19-Supuestos!$B$20)-C15 -> 3600
A18: Total pasivo | B18: =B16+B17 -> 7850 | C18: =C16+C17 -> 7654.0155
A19: Capital social | B19: =Historicos!C33 -> 5000 | C19: =B19 -> 5000
A20: Reservas | B20: =Historicos!C34 -> 1500 | C20: =B20+Historicos!C16*Supuestos!$B$22 -> 1653.7
A21: Resultados acumulados | B21: =Historicos!C35 -> 1763 | C21: =B21+Historicos!C16*(1-Supuestos!$B$22-Supuestos!$B$23) -> 2377.8
A22: Utilidad del ejercicio | B22: =Historicos!C36 -> 1537 | C22: =ER_Proy!C15 -> 1716.2829
A23: Total patrimonio | B23: =SUM(B19:B22) -> 9800 | C23: =SUM(C19:C22) -> 10747.783
A24: Total pasivo + patrimonio | B24: =B18+B23 -> 17650 | C24: =C18+C23 -> 18401.798
A25: Verificación (debe ser 0) | B25: =B11-B24 -> 0 | C25: =C11-C24 -> 0

Sheet Flujo_Indirecto
A1: Estado de flujos de efectivo - método indirecto (NIC 7)
A2: Cifras en millones de COP. Año 0 = comparativo derivado de los balances históricos; Año 1 = proyección.
A4: Concepto | B4: Año 0 (comparativo) | C4: Año 1 (proyectado) | D4: Referencia NIC 7
A5: Flujos de efectivo de actividades de operación
A6: Utilidad neta del período | B6: =Historicos!C16 -> 1537 | C6: =ER_Proy!C15 -> 1716.2829 | D6: Párr. 18(b), 20
A7: Ajustes por partidas no monetarias:
A8: Depreciación y amortización | B8: =Historicos!C11 -> 950 | C8: =ER_Proy!C10 -> 1020 | D8: Párr. 20(b)
A9: Cambios en el capital de trabajo operativo:
A10: (Aumento) en cuentas por cobrar | B10: =-(Historicos!C20-Historicos!B20) -> -300 | C10: =-(Balance_Proy!C6-Balance_Proy!B6) -> -293.29315 | D10: Párr. 20(a)
A11: (Aumento) en inventarios | B11: =-(Historicos!C21-Historicos!B21) -> -200 | C11: =-(Balance_Proy!C7-Balance_Proy!B7) -> -183.37162 | D11: Párr. 20(a)
A12: (Aumento) en gastos pagados por anticipado | B12: =-(Historicos!C22-Historicos!B22) -> -20 | C12: =-(Balance_Proy!C8-Balance_Proy!B8) -> -18.592 | D12: Párr. 20(a)
A13: Aumento en proveedores | B13: =Historicos!C26-Historicos!B26 -> 150 | C13: =Balance_Proy!C12-Balance_Proy!B12 -> 140.41828 | D13: Párr. 20(a)
A14: Aumento en obligaciones laborales | B14: =Historicos!C27-Historicos!B27 -> 30 | C14: =Balance_Proy!C13-Balance_Proy!B13 -> 30.9024 | D14: Párr. 20(a)
A15: Aumento en impuesto de renta por pagar | B15: =Historicos!C28-Historicos!B28 -> 30 | C15: =Balance_Proy!C14-Balance_Proy!B14 -> 32.694835 | D15: Párr. 20(a)
A16: Flujo neto de efectivo de actividades de operación | B16: =B6+B8+SUM(B10:B15) -> 2177 | C16: =C6+C8+SUM(C10:C15) -> 2445.0416
A17: Flujos de efectivo de actividades de inversión
A18: Adquisición de propiedades, planta y equipo | B18: =-((Historicos!C24-Historicos!B24)+Historicos!C11) -> -550 | C18: =-Supuestos!$B$10 -> -1200 | D18: Párr. 16(a)
A19: Flujo neto de efectivo de actividades de inversión | B19: =B18 -> -550 | C19: =C18 -> -1200
A20: Flujos de efectivo de actividades de financiación
A21: Cobros por nuevos préstamos | B21: 0 | C21: =Supuestos!$B$19 -> 600 | D21: Párr. 17(c)
A22: Pagos de préstamos (amortización) | B22: =(Historicos!C29+Historicos!C31)-(Historicos!B29+Historicos!B31)-B21 -> -1000 | C22: =-Supuestos!$B$20 -> -1000 | D22: Párr. 17(d)
A23: Dividendos pagados | B23: =-(Historicos!B37+Historicos!C16-Historicos!C37) -> -700 | C23: =-Historicos!C16*Supuestos!$B$23 -> -768.5 | D23: Párr. 34
A24: Flujo neto de efectivo de actividades de financiación | B24: =SUM(B21:B23) -> -1700 | C24: =SUM(C21:C23) -> -1168.5
A25: Aumento (disminución) neto de efectivo | B25: =B16+B19+B24 -> -73 | C25: =C16+C19+C24 -> 76.541628
A26: Efectivo y equivalentes al inicio del período | B26: =Historicos!B19 -> 1523 | C26: =Historicos!C19 -> 1450
A27: Efectivo y equivalentes al final del período | B27: =B25+B26 -> 1450 | C27: =C25+C26 -> 1526.5416 | D27: Párr. 45
A28: Efectivo según balance | B28: =Historicos!C19 -> 1450 | C28: =Balance_Proy!C5 -> 1526.5416
A29: Diferencia (debe ser 0) | B29: =B27-B28 -> 0 | C29: =C27-C28 -> 0
A30: Información complementaria a revelar
A31: Intereses pagados (clasificados en operación) | B31: =Historicos!C13 -> 410 | C31: =ER_Proy!C12 -> 424 | D31: Párr. 31-33
A32: Impuesto de renta pagado (clasificado en operación) | B32: =Historicos!C15-(Historicos!C28-Historicos!B28) -> 798 | C32: =ER_Proy!C14-(Balance_Proy!C14-Balance_Proy!B14) -> 891.45748 | D32: Párr. 35-36

Sheet Flujo_Directo
A1: Estado de flujos de efectivo - método directo (conciliación)
A2: Año 1 proyectado. Presenta cobros y pagos brutos (NIC 7 párr. 19 y 21) y debe coincidir con el método indirecto.
A4: Concepto | B4: Año 1 (proyectado) | C4: Referencia NIC 7
A5: Flujos de efectivo de actividades de operación
A6: Cobros procedentes de clientes | B6: =ER_Proy!C5-(Balance_Proy!C6-Balance_Proy!B6) -> 21565.907 | C6: Párr. 14(a), 21(a)
A7: Pagos a proveedores por bienes | B7: =-(ER_Proy!C6+(Balance_Proy!C7-Balance_Proy!B7)-(Balance_Proy!C12-Balance_Proy!B12)) -> -14142.137 | C7: Párr. 14(c), 21(b)
A8: Pagos por gastos de administración y ventas (personal y otros) | B8: =-(ER_Proy!C8+ER_Proy!C9+(Balance_Proy!C8-Balance_Proy!B8)-(Balance_Proy!C13-Balance_Proy!B13)) -> -3663.2704 | C8: Párr. 14(d), 21(b)
A9: Intereses pagados | B9: =-ER_Proy!C12 -> -424 | C9: Párr. 31-33
A10: Impuesto de renta pagado | B10: =-(ER_Proy!C14-(Balance_Proy!C14-Balance_Proy!B14)) -> -891.45748 | C10: Párr. 35-36
A11: Flujo neto de efectivo de actividades de operación | B11: =SUM(B6:B10) -> 2445.0416
A12: Flujos de efectivo de actividades de inversión
A13: Adquisición de propiedades, planta y equipo | B13: =Flujo_Indirecto!C18 -> -1200 | C13: Párr. 16(a)
A14: Flujo neto de efectivo de actividades de inversión | B14: =B13 -> -1200
A15: Flujos de efectivo de actividades de financiación
A16: Cobros por nuevos préstamos | B16: =Flujo_Indirecto!C21 -> 600 | C16: Párr. 17(c)
A17: Pagos de préstamos | B17: =Flujo_Indirecto!C22 -> -1000 | C17: Párr. 17(d)
A18: Dividendos pagados | B18: =Flujo_Indirecto!C23 -> -768.5 | C18: Párr. 34
A19: Flujo neto de efectivo de actividades de financiación | B19: =SUM(B16:B18) -> -1168.5
A20: Aumento (disminución) neto de efectivo | B20: =B11+B14+B19 -> 76.541628
A21: Efectivo y equivalentes al inicio del período | B21: =Historicos!C19 -> 1450
A22: Efectivo y equivalentes al final del período | B22: =B20+B21 -> 1526.5416
A23: Diferencia de operación vs. método indirecto (debe ser 0) | B23: =B11-Flujo_Indirecto!C16 -> 0

Sheet Ratios
A1: Ratios de liquidez, actividad y endeudamiento
A2: Días calculados con saldos de cierre. Año 1 = proyectado.
A4: Ratio | B4: Año -1 | C4: Año 0 | D4: Año 1 (proy.) | E4: Lectura
A5: Razón corriente (veces) | B5: =Historicos!B23/Historicos!B30 -> 2.0887363 | C5: =Historicos!C23/Historicos!C30 -> 2.0909091 | D5: =Balance_Proy!C9/Balance_Proy!C16 -> 2.1267305 | E5: Capacidad de cubrir el pasivo corriente con el activo corriente.
A6: Prueba ácida (veces) | B6: =(Historicos!B23-Historicos!B21)/Historicos!B30 -> 1.292033 | C6: =(Historicos!C23-Historicos!C21)/Historicos!C30 -> 1.2857143 | D6: =(Balance_Proy!C9-Balance_Proy!C7)/Balance_Proy!C16 -> 1.3168245 | E6: Liquidez sin depender de la venta de inventarios.
A7: Razón de efectivo (veces) | B7: =Historicos!B19/Historicos!B30 -> 0.41840659 | C7: =Historicos!C19/Historicos!C30 -> 0.37662338 | D7: =Balance_Proy!C5/Balance_Proy!C16 -> 0.37655051 | E7: Efectivo disponible frente a obligaciones de corto plazo.
A8: Capital de trabajo neto (COP mm) | B8: =Historicos!B23-Historicos!B30 -> 3963 | C8: =Historicos!C23-Historicos!C30 -> 4200 | D8: =Balance_Proy!C9-Balance_Proy!C16 -> 4567.7829 | E8: Colchón de recursos corrientes tras cubrir el pasivo corriente.
A9: Días de cartera | B9: =Historicos!B20/Historicos!B6*365 -> 59.51087 | C9: =Historicos!C20/Historicos!C6*365 -> 59.51087 | D9: =Balance_Proy!C6/ER_Proy!C5*365 -> 60 | E9: Plazo medio de cobro.
A10: Días de inventario | B10: =Historicos!B21/Historicos!B7*365 -> 88.503344 | C10: =Historicos!C21/Historicos!C7*365 -> 86.671773 | D10: =Balance_Proy!C7/ER_Proy!C6*365 -> 85 | E10: Plazo medio de permanencia del inventario.
A11: Días de proveedores | B11: =Historicos!B26/Historicos!B7*365 -> 59.51087 | C11: =Historicos!C26/Historicos!C7*365 -> 58.713137 | D11: =Balance_Proy!C12/ER_Proy!C6*365 -> 58 | E11: Plazo medio de pago.
A12: Ciclo de conversión de efectivo (días) | B12: =B9+B10-B11 -> 88.503344 | C12: =C9+C10-C11 -> 87.469506 | D12: =D9+D10-D11 -> 87 | E12: Días que el efectivo permanece inmovilizado en el ciclo operativo.
A13: Endeudamiento total (pasivo / activo) | B13: =Historicos!B32/Historicos!B25 -> 0.49082543 | C13: =Historicos!C32/Historicos!C25 -> 0.44475921 | D13: =Balance_Proy!C18/Balance_Proy!C11 -> 0.41593845 | E13: Proporción de los activos financiada con terceros.
A14: Cobertura de intereses (veces) | B14: =Historicos!B12/Historicos!B13 -> 6.1052632 | C14: =Historicos!C12/Historicos!C13 -> 6.7682927 | D14: =ER_Proy!C11/ER_Proy!C12 -> 7.2274415 | E14: Utilidad operacional frente a gastos financieros.
A15: Margen neto | B15: =Historicos!B16/Historicos!B6 -> 0.068532609 | C15: =Historicos!C16/Historicos!C6 -> 0.075938735 | D15: =ER_Proy!C15/ER_Proy!C5 -> 0.078515356 | E15: Utilidad neta por cada peso vendido.

Sheet Validacion
A1: Validación del modelo y de la presentación NIC 7
A2: Sección 1: controles automáticos. Sección 2: lista de verificación. Sección 3: registro de la revisión por experto técnico (completar).
A4: Control automático | B4: Diferencia / valor | C4: Resultado
A5: Balance histórico Año -1 cuadra | B5: =Historicos!B39 -> 0 | C5: =IF(ABS(B5)<0.5,"OK","REVISAR") -> OK
A6: Balance histórico Año 0 cuadra | B6: =Historicos!C39 -> 0 | C6: =IF(ABS(B6)<0.5,"OK","REVISAR") -> OK
A7: Balance proyectado Año 1 cuadra | B7: =Balance_Proy!C25 -> 0 | C7: =IF(ABS(B7)<0.5,"OK","REVISAR") -> OK
A8: Efectivo final comparativo Año 0 = efectivo del balance | B8: =Flujo_Indirecto!B29 -> 0 | C8: =IF(ABS(B8)<0.5,"OK","REVISAR") -> OK
A9: Efectivo final Año 1 (flujo) = efectivo del balance | B9: =Flujo_Indirecto!C29 -> 0 | C9: =IF(ABS(B9)<0.5,"OK","REVISAR") -> OK
A10: Flujo de operación directo = indirecto | B10: =Flujo_Directo!B23 -> 0 | C10: =IF(ABS(B10)<0.5,"OK","REVISAR") -> OK
A11: Efectivo final Año 1 no es negativo | B11: =Balance_Proy!C5 -> 1526.5416 | C11: =IF(B11>=0,"OK","REVISAR") -> OK
A13: Lista de verificación NIC 7 | B13: Cumple | C13: Evidencia
A14: Flujos clasificados en operación, inversión y financiación (párr. 10) | B14: Sí | C14: Flujo_Indirecto filas 5-24
A15: Método de operación identificado y justificado (párr. 18-20) | B15: Sí | C15: Informe, sección «Selección y justificación del método»
A16: Ajustes por partidas no monetarias y cambios en capital de trabajo (párr. 20) | B16: Sí | C16: Flujo_Indirecto filas 8-15
A17: Intereses pagados e impuesto pagado revelados por separado (párr. 31 y 35) | B17: Sí | C17: Flujo_Indirecto filas 31-32
A18: Dividendos pagados clasificados de forma consistente (párr. 34) | B18: Sí | C18: Flujo_Indirecto fila 23
A19: Conciliación del efectivo final con el balance (párr. 45) | B19: Sí | C19: Flujo_Indirecto filas 27-29
A20: Información comparativa del período anterior (NIC 1 párr. 38) | B20: Sí | C20: Columna Año 0 de Flujo_Indirecto
A21: Transacciones sin efectivo excluidas (párr. 43) | B21: Sí | C21: No se proyectan transacciones sin efecto en el efectivo
A23: Registro de revisión por experto técnico | B23: Dato
A24: Nombre y cargo del revisor
A25: Fecha de revisión
A27: Hallazgo u observación del revisor | B27: Párrafo NIC 7 / hoja | C27: Ajuste realizado
A28: EJEMPLO (borrar): Clasificar los intereses pagados en financiación en lugar de operación. | B28: Párr. 33 / Flujo_Indirecto | C28: Se mantiene en operación y se revela por separado; se documenta la política.
A35: Amarillo = campos que debe completar el estudiante con la revisión real (no se inventa el resultado de la revisión).

Sheet Anexo_Formulas
A1: Anexo: fórmulas utilizadas
A2: Descripción conceptual y ubicación en el libro (Año 1).
A4: Concepto | B4: Fórmula conceptual | C4: Ubicación
A5: Ventas Año 1 | B5: Ventas Año 0 x (1 + crecimiento) | C5: ER_Proy!C5
A6: Costo de ventas | B6: Ventas Año 1 x % costo | C6: ER_Proy!C6
A7: Depreciación | B7: Tasa x (PP&E neto inicial + 50 % del capex) | C7: ER_Proy!C10
A8: Gastos financieros | B8: Tasa x (deuda inicial + 50 % del nuevo crédito) | C8: ER_Proy!C12
A9: Impuesto de renta | B9: MAX(0; utilidad antes de impuestos) x tarifa | C9: ER_Proy!C14
A10: Cuentas por cobrar | B10: Ventas x días de cartera / 365 | C10: Balance_Proy!C6
A11: Inventarios | B11: Costo de ventas x días de inventario / 365 | C11: Balance_Proy!C7
A12: Proveedores | B12: Costo de ventas x días de proveedores / 365 | C12: Balance_Proy!C12
A13: PP&E neto | B13: PP&E inicial + capex - depreciación | C13: Balance_Proy!C10
A14: Deuda no corriente | B14: Deuda inicial + nuevo crédito - amortización - porción corriente | C14: Balance_Proy!C17
A15: Flujo de operación (indirecto) | B15: Utilidad neta + depreciación +/- cambios en capital de trabajo | C15: Flujo_Indirecto!C16
... A22: Ciclo de conversión de efectivo | B22: Días cartera + días inventario - días proveedores | C22: Ratios!B12:D12
